health_checks/__init__.py
health_checks/base.py
health_checks/fastapi_healthcheck.py
health_checks/file_based.py
health_checks/http_based.py
health_checks/litestar_healthcheck.py
health_checks/py.typed
health_checks-1.2.2.dist-info/METADATA
health_checks-1.2.2.dist-info/WHEEL
health_checks-1.2.2.dist-info/RECORD
