Metadata-Version: 2.4
Name: health-checks
Version: 1.2.2
Summary: Library for health checks
Author: community-of-python
Keywords: application-monitoring,diagnostics,endpoint-health,fastapi-health,health-check,health-middleware,litestar-health,service-status,system-status,uptime-monitoring
Classifier: Intended Audience :: Developers
Classifier: Operating System :: MacOS
Classifier: Operating System :: Microsoft
Classifier: Operating System :: POSIX :: Linux
Classifier: Programming Language :: Python
Classifier: Programming Language :: Python :: 3
Classifier: Programming Language :: Python :: 3 :: Only
Classifier: Programming Language :: Python :: 3.9
Classifier: Programming Language :: Python :: 3.10
Classifier: Programming Language :: Python :: 3.11
Classifier: Programming Language :: Python :: 3.12
Classifier: Topic :: Software Development :: Build Tools
Classifier: Typing :: Typed
Requires-Python: <4,>=3.9
Requires-Dist: aiofiles>=0.6.0
Requires-Dist: aiopath>=0.5.6
Provides-Extra: fastapi
Requires-Dist: fastapi>=0.100; extra == 'fastapi'
Provides-Extra: litestar
Requires-Dist: litestar>=2; extra == 'litestar'
